miniquant_ioc/__init__.py
miniquant_ioc/_version.py
miniquant_ioc/application.py
miniquant_ioc/config_example.py
miniquant_ioc/main.py
miniquant_ioc/reader.py
miniquant_ioc/histoview/__init__.py
miniquant_ioc/histoview/display.py
miniquant_ioc/histoview/historead.py
miniquant_ioc/histoview/nxsave.py
miniquant_ioc/histoview/nxsave_main.py
miniquant_ioc/histoview/roi.py
miniquant_ioc/tau0/application.py
miniquant_ioc/tau0/diode.py
miniquant_ioc/tau0/main.py
miniquant_ioc-0.1.20.dist-info/licenses/LICENSE
miniquant_ioc-0.1.20.dist-info/METADATA
miniquant_ioc-0.1.20.dist-info/WHEEL
miniquant_ioc-0.1.20.dist-info/entry_points.txt
miniquant_ioc-0.1.20.dist-info/top_level.txt
miniquant_ioc-0.1.20.dist-info/RECORD
