Metadata-Version: 2.4
Name: miniquant-ioc
Version: 0.1.20
Summary: Python interface for the Harp class of PicoQuant's time interval analysers and photon counters
Author-email: Florin Boariu <florin.pt@rootshell.ro>
Project-URL: Source Code, https://gitlab.com/kmc3-xpp/miniquant-ioc/
Project-URL: Bug Tracker, https://gitlab.com/kmc3-xpp/miniquant-ioc/-/issues
Classifier: Programming Language :: Python :: 3
Classifier: License :: OSI Approved :: GNU General Public License v3 or later (GPLv3+)
Classifier: Operating System :: POSIX :: Linux
Classifier: Development Status :: 2 - Pre-Alpha
Classifier: Environment :: Console
Classifier: Intended Audience :: Science/Research
Classifier: Topic :: Scientific/Engineering
Requires-Python: >=3.8
License-File: LICENSE
Requires-Dist: softioc
Requires-Dist: numpy
Requires-Dist: miniquant>=0.3.4
Requires-Dist: libusb1
Requires-Dist: schema
Requires-Dist: emmi[softioc]==0.9.3
Requires-Dist: pyyaml
Requires-Dist: caproto
Requires-Dist: xarray
Provides-Extra: test
Requires-Dist: pytest; extra == "test"
Requires-Dist: pytest-cov; extra == "test"
Requires-Dist: pytest-asyncio; extra == "test"
Dynamic: license-file
